plugin/__init__.py
plugin/main.py
armasec_subscriptions-0.1.1.dist-info/LICENSE.md
armasec_subscriptions-0.1.1.dist-info/METADATA
armasec_subscriptions-0.1.1.dist-info/WHEEL
armasec_subscriptions-0.1.1.dist-info/entry_points.txt
armasec_subscriptions-0.1.1.dist-info/RECORD
