Metadata-Version: 2.1
Name: armasec-subscriptions
Version: 0.1.1
Summary: Armasec plugin for verifying subscribed user access
Home-page: https://github.com/omnivector-solutions/armasec
License: MIT
Author: Omnivector Engineering Team
Author-email: info@omnivector.solutions
Requires-Python: >=3.8,<4.0
Classifier: License :: OSI Approved :: MIT License
Classifier: Programming Language :: Python :: 3
Classifier: Programming Language :: Python :: 3.8
Classifier: Programming Language :: Python :: 3.9
Classifier: Programming Language :: Python :: 3.10
Classifier: Programming Language :: Python :: 3.11
Classifier: Programming Language :: Python :: 3.12
Classifier: Programming Language :: Python :: 3.13
Requires-Dist: armasec (>=2.0.1,<3.0.0)
Requires-Dist: cachetools (>=5.3.3,<6.0.0)
Requires-Dist: httpx (>=0.27.0,<0.28.0)
Project-URL: CHANGELOG, https://github.com/omnivector-solutions/armasec-subscriptions/blob/main/CHANGELOG.md
Project-URL: Documentation, https://omnivector-solutions.github.io/armasec
Project-URL: Repository, https://github.com/omnivector-solutions/armasec
